djangocms_oembed/__init__.py
djangocms_oembed/cms_plugins.py
djangocms_oembed/models.py
djangocms_oembed/oembed_providers.py
djangocms_oembed/migrations/0001_initial.py
djangocms_oembed/migrations/__init__.py
djangocms_oembed/templates/djangocms_oembed/plugins/video.html
djangocms_oembed/templates/djangocms_oembed/plugins/video_iframe.html
djangocms_oembed-0.5.dist-info/DESCRIPTION.rst
djangocms_oembed-0.5.dist-info/METADATA
djangocms_oembed-0.5.dist-info/metadata.json
djangocms_oembed-0.5.dist-info/RECORD
djangocms_oembed-0.5.dist-info/top_level.txt
djangocms_oembed-0.5.dist-info/WHEEL
