Metadata-Version: 2.0
Name: djangocms-oembed
Version: 0.5
Summary: A set of oembed plugins for django CMS.
Home-page: http://github.com/divio/djangocms-oembed
Author: Divio AG
Author-email: developers@divio.ch
License: BSD
Platform: OS Independent
Classifier: Development Status :: 4 - Beta
Classifier: Framework :: Django
Classifier: Intended Audience :: Developers
Classifier: License :: OSI Approved :: BSD License
Classifier: Operating System :: OS Independent
Classifier: Programming Language :: Python
Classifier: Topic :: Internet :: WWW/HTTP
Requires-Dist: Django (>=1.4)
Requires-Dist: django-cms
Requires-Dist: pyquery
Requires-Dist: micawber
